cmmn/__init__.py
cmmn-0.0.1.dist-info/METADATA
cmmn-0.0.1.dist-info/WHEEL
cmmn-0.0.1.dist-info/top_level.txt
cmmn-0.0.1.dist-info/RECORD
