Metadata-Version: 2.1
Name: cmmn
Version: 0.0.1
Summary: Python Package Template
Home-page: UNKNOWN
Author: UNKNOWN
Author-email: UNKNOWN
License: UNKNOWN
Platform: UNKNOWN
